meanshift_rs-0.9.3.dist-info/METADATA
meanshift_rs-0.9.3.dist-info/WHEEL
meanshift_rs/__init__.py
meanshift_rs/meanshift.py
meanshift_rs/meanshift_rs.cpython-39-x86_64-linux-gnu.so
meanshift_rs-0.9.3.dist-info/RECORD
