Metadata-Version: 2.1
Name: meanshift-rs
Version: 0.9.3
Summary: Rust version of the MeanShift clustering algorithm that does not need a predefined number of clusters.
Author: Phillip Wenig <info@pwenig.de>
Author-email: Phillip Wenig <info@pwenig.de>
License: MIT
Project-URL: Source Code, https://github.com/wenig/meanshift-rs
